django_admin_sbf/__init__.py
django_admin_sbf/admin.py
django_admin_sbf/admin_forms.py
django_admin_sbf/apps.py
django_admin_sbf/tests.py
django_admin_sbf/migrations/__init__.py
django_admin_sbf/templates/admin/sbf_custom_change_list.html
django_admin_sbf/templates/admin/sbf_custom_search_form.html
django_admin_sbf/templatetags/__init__.py
django_admin_sbf/templatetags/custom_search_form.py
django_admin_sbf-0.5.dist-info/METADATA
django_admin_sbf-0.5.dist-info/WHEEL
django_admin_sbf-0.5.dist-info/top_level.txt
django_admin_sbf-0.5.dist-info/RECORD
