Metadata-Version: 2.1
Name: django-admin-sbf
Version: 0.5
Summary: A Django admin app to search by specific field instead of all fields
Home-page: https://github.com/anuj9196/django-admin-sbf
Author: Anuj Sharma
Author-email: contact@anujs.in
License: UNKNOWN
Platform: UNKNOWN
Classifier: Environment :: Web Environment
Classifier: Framework :: Django
Classifier: Framework :: Django :: 2.2
Classifier: Intended Audience :: Developers
Classifier: License :: OSI Approved :: BSD License
Classifier: Operating System :: OS Independent
Classifier: Programming Language :: Python
Classifier: Programming Language :: Python :: 3
Classifier: Topic :: Internet :: WWW/HTTP
Classifier: Topic :: Software Development :: Libraries :: Python Modules
